odoo/addons/hr_timesheet_autofill_project_off/README.rst
odoo/addons/hr_timesheet_autofill_project_off/__init__.py
odoo/addons/hr_timesheet_autofill_project_off/__manifest__.py
odoo/addons/hr_timesheet_autofill_project_off/i18n/hr_timesheet_autofill_project_off.pot
odoo/addons/hr_timesheet_autofill_project_off/i18n/it.po
odoo/addons/hr_timesheet_autofill_project_off/models/__init__.py
odoo/addons/hr_timesheet_autofill_project_off/models/hr_timesheet.py
odoo/addons/hr_timesheet_autofill_project_off/readme/CONTRIBUTORS.md
odoo/addons/hr_timesheet_autofill_project_off/readme/DESCRIPTION.md
odoo/addons/hr_timesheet_autofill_project_off/readme/USAGE.md
odoo/addons/hr_timesheet_autofill_project_off/static/description/icon.png
odoo/addons/hr_timesheet_autofill_project_off/static/description/index.html
odoo/addons/hr_timesheet_autofill_project_off/static/img/01_project_autofill_without_addon.png
odoo/addons/hr_timesheet_autofill_project_off/static/img/02_no_project_autofill_with_addon.png
odoo/addons/hr_timesheet_autofill_project_off/tests/__init__.py
odoo/addons/hr_timesheet_autofill_project_off/tests/test_account_analytic_line_default_get.py
odoo_addon_hr_timesheet_autofill_project_off-17.0.1.0.0.4.dist-info/METADATA
odoo_addon_hr_timesheet_autofill_project_off-17.0.1.0.0.4.dist-info/WHEEL
odoo_addon_hr_timesheet_autofill_project_off-17.0.1.0.0.4.dist-info/top_level.txt
odoo_addon_hr_timesheet_autofill_project_off-17.0.1.0.0.4.dist-info/RECORD
