Metadata-Version: 2.1
Name: odoo-addon-hr_timesheet_autofill_project_off
Version: 17.0.1.0.0.4
Requires-Python: >=3.10
Requires-Dist: odoo>=17.0a,<17.1dev
Summary: Timesheet - Autofill project off
Home-page: https://github.com/OCA/timesheet
License: AGPL-3
Author: Innovara, Odoo Community Association (OCA)
Author-email: support@odoo-community.org
Classifier: Programming Language :: Python
Classifier: Framework :: Odoo
Classifier: Framework :: Odoo :: 17.0
Classifier: License :: OSI Approved :: GNU Affero General Public License v3
